llm_graph_kit/.gitkeep
llm_graph_kit/__init__.py
llm_graph_kit/graph_logger.py
llm_graph_kit/llm_graph.py
llm_graph_kit-0.2.1.dist-info/WHEEL
llm_graph_kit-0.2.1.dist-info/METADATA
llm_graph_kit-0.2.1.dist-info/RECORD
