Metadata-Version: 2.3
Name: llm-graph-kit
Version: 0.2.1
Summary: Add your description here
Requires-Dist: mlx-augllm>=1.5
Requires-Python: >=3.13.9
Project-URL: Homepage, https://github.com/ToPo-ToPo-ToPo/llm_graph
